raspy_cal/__init__.py
raspy_cal/__main__.py
raspy_cal/default.py
raspy_cal/lowlevel.py
raspy_cal/main.py
raspy_cal/settings.py
raspy_cal/frontend/__init__.py
raspy_cal/frontend/display.py
raspy_cal/frontend/gui.py
raspy_cal/frontend/input.py
raspy_cal/midlevel/__init__.py
raspy_cal/midlevel/calibrators.py
raspy_cal/midlevel/data.py
raspy_cal/midlevel/eval.py
raspy_cal/midlevel/params.py
raspy_cal-1.2.0.dist-info/LICENSE
raspy_cal-1.2.0.dist-info/METADATA
raspy_cal-1.2.0.dist-info/WHEEL
raspy_cal-1.2.0.dist-info/top_level.txt
raspy_cal-1.2.0.dist-info/RECORD
