Metadata-Version: 2.1
Name: raspy-cal
Version: 1.2.0
Summary: A HEC-RAS automatic calibration application
Home-page: https://github.com/quantum-dan/raspy-cal
Author: Daniel Philippus
Author-email: daniel@dphilippus.com
Project-URL: Bug Tracker, https://github.com/quantum-dan/raspy-cal/issues
Classifier: Programming Language :: Python :: 3
Classifier: License :: OSI Approved :: GNU General Public License v3 (GPLv3)
Classifier: Operating System :: Microsoft :: Windows
Requires-Python: >=3.6
License-File: LICENSE
Requires-Dist: pyrasfile
Requires-Dist: pywin32
Requires-Dist: raspy-auto >=1.1.0
Requires-Dist: scipy
Requires-Dist: HydroErr
Requires-Dist: matplotlib
Requires-Dist: platypus-opt
